stream_delay.py
stream_delay-0.1.dist-info/LICENSE
stream_delay-0.1.dist-info/METADATA
stream_delay-0.1.dist-info/WHEEL
stream_delay-0.1.dist-info/entry_points.txt
stream_delay-0.1.dist-info/top_level.txt
stream_delay-0.1.dist-info/RECORD
