Metadata-Version: 2.1
Name: stream-delay
Version: 0.1
Summary: Stream a file or stdin one line at a time with a delay
Home-page: https://github.com/simonw/stream-delay
Author: Simon Willison
License: Apache License, Version 2.0
Project-URL: Issues, https://github.com/simonw/stream-delay/issues
Project-URL: CI, https://github.com/simonw/stream-delay/actions
Project-URL: Changelog, https://github.com/simonw/stream-delay/releases
Platform: UNKNOWN
Requires-Python: >=3.6
License-File: LICENSE
Provides-Extra: test
Requires-Dist: pytest ; extra == 'test'
